number_names.py
number_names-0.1.2.dist-info/LICENSE
number_names-0.1.2.dist-info/WHEEL
number_names-0.1.2.dist-info/METADATA
number_names-0.1.2.dist-info/RECORD
