Metadata-Version: 2.3
Name: number_names
Version: 0.1.2
Summary: This module provides functions for getting the English names of numbers.
Author: Tom Fryers
Requires-Python: >=3.9
Classifier: Development Status :: 4 - Beta
Classifier: Programming Language :: Python :: 3
Classifier: License :: OSI Approved :: GNU General Public License v3 or later (GPLv3+)
Classifier: Operating System :: OS Independent
Project-URL: Home, https://gitlab.com/Tom_Fryers/number_names
